.travis.yml
AUTHORS
ChangeLog
LICENSE
MANIFEST.in
README.rst
requirements.txt
setup.cfg
setup.py
.tx/config
dbtemplates/__init__.py
dbtemplates/admin.py
dbtemplates/conf.py
dbtemplates/loader.py
dbtemplates/models.py
dbtemplates/test_cases.py
dbtemplates/test_settings.py
dbtemplates/locale/da/LC_MESSAGES/django.mo
dbtemplates/locale/da/LC_MESSAGES/django.po
dbtemplates/locale/de/LC_MESSAGES/django.mo
dbtemplates/locale/de/LC_MESSAGES/django.po
dbtemplates/locale/en/LC_MESSAGES/django.mo
dbtemplates/locale/en/LC_MESSAGES/django.po
dbtemplates/locale/fi/LC_MESSAGES/django.mo
dbtemplates/locale/fi/LC_MESSAGES/django.po
dbtemplates/locale/fr/LC_MESSAGES/django.mo
dbtemplates/locale/fr/LC_MESSAGES/django.po
dbtemplates/locale/he/LC_MESSAGES/django.mo
dbtemplates/locale/he/LC_MESSAGES/django.po
dbtemplates/locale/it/LC_MESSAGES/django.mo
dbtemplates/locale/it/LC_MESSAGES/django.po
dbtemplates/locale/pt_BR/LC_MESSAGES/django.mo
dbtemplates/locale/pt_BR/LC_MESSAGES/django.po
dbtemplates/locale/ru/LC_MESSAGES/django.mo
dbtemplates/locale/ru/LC_MESSAGES/django.po
dbtemplates/locale/zh_CN/LC_MESSAGES/django.mo
dbtemplates/locale/zh_CN/LC_MESSAGES/django.po
dbtemplates/management/__init__.py
dbtemplates/management/commands/__init__.py
dbtemplates/management/commands/check_template_syntax.py
dbtemplates/management/commands/create_error_templates.py
dbtemplates/management/commands/sync_templates.py
dbtemplates/migrations/0001_initial.py
dbtemplates/migrations/__init__.py
dbtemplates/south_migrations/0001_initial.py
dbtemplates/south_migrations/0002_auto__del_unique_template_name.py
dbtemplates/south_migrations/__init__.py
dbtemplates/static/dbtemplates/css/django.css
dbtemplates/static/dbtemplates/css/editor.css
dbtemplates/static/dbtemplates/js/codemirror.js
dbtemplates/static/dbtemplates/js/editor.js
dbtemplates/static/dbtemplates/js/highlight.js
dbtemplates/static/dbtemplates/js/mirrorframe.js
dbtemplates/static/dbtemplates/js/parsedjango.js
leonardo_dbtemplates.egg-info/PKG-INFO
leonardo_dbtemplates.egg-info/SOURCES.txt
leonardo_dbtemplates.egg-info/dependency_links.txt
leonardo_dbtemplates.egg-info/not-zip-safe
leonardo_dbtemplates.egg-info/pbr.json
leonardo_dbtemplates.egg-info/requires.txt
leonardo_dbtemplates.egg-info/top_level.txt
