Metadata-Version: 1.1
Name: leonardo-dbtemplates
Version: 1.0.0a1
Summary: Template loader for templates stored in the database. Leonardo Fork from Jannis Leidel
Home-page: https://github.com/django-leonardo/django-dbtemplates
Author: Michael Kuty
Author-email: mail@michaelkuty.eu
License: UNKNOWN
Platform: UNKNOWN
Classifier: Development Status :: 5 - Production/Stable
Classifier: Framework :: Django
Classifier: Intended Audience :: Developers
Classifier: License :: OSI Approved :: BSD License
Classifier: Operating System :: OS Independent
Classifier: Programming Language :: Python
Classifier: Programming Language :: Python :: 2.6
Classifier: Programming Language :: Python :: 2.7
Classifier: Programming Language :: Python :: 3
Classifier: Programming Language :: Python :: 3.3
Classifier: Programming Language :: Python :: 3.4
Classifier: Topic :: Software Development
Classifier: Topic :: Software Development :: Libraries :: Application Frameworks
